MANIFEST.in
README.md
setup.cfg
setup.py
bin/ppaxe
ppaxe/__init__.py
ppaxe/core.py
ppaxe/feature_names.py
ppaxe/report.py
ppaxe.egg-info/PKG-INFO
ppaxe.egg-info/SOURCES.txt
ppaxe.egg-info/dependency_links.txt
ppaxe.egg-info/not-zip-safe
ppaxe.egg-info/requires.txt
ppaxe.egg-info/top_level.txt
ppaxe/data/RF_scikit.pkl