Metadata-Version: 1.0
Name: ppaxe
Version: 1.1
Summary: Protein-Protein interactions extractor from PubMed articles
Home-page: http://github.com/scastlara/ppaxe
Author: S. Castillo-Lara
Author-email: s.cast.lara@gmail.com
License: GPL-3.0
Platform: UNKNOWN
